Workbook

Sheet Goals Input
B3: GOALS TABLE
P4: According to First year allocation | U4: According to the Glide Path Table
A5: Goal Name | B5: Category | C5: Priority Level | D5: Target Amount (Today ₹) | E5: Time Horizon (Years) | F5: Inflation % | G5: Future Value | H5: Current Savings | I5: Monthly SIP (assumed) | J5: Required Return | K5: Present Value | L5: Risk Profile | M5: Weight | N5: Equity % | O5: Debt % | P5: Precious Metals % | Q5: Alternatives % | R5: Goal SIP (according to weight) | S5: Years Left | T5: Risk Stage | U5: Equity % | V5: Debt % | W5: Precious Metals % | X5: Alternatives %
A6: Emergency Fund | B6: Essential | C6: High | D6: 500000 | E6: 1 | F6: 0.06 | G6: =D6*(1+F6)^E6 -> 530000 | H6: 100000 | I6: 20000 | J6: 0.08 | K6: =G6/(1+J6)^E6 -> 490740.74 | L6: =IF(E6<=3,"Conservative",IF(E6<=10,"Moderate","Aggressive")) -> Conservative | M6: =G6/$G$14 -> 0.0051545787 | N6: =VLOOKUP(L6,Asset_Allocation!$A$6:$L$8,2,FALSE) -> 0.2 | O6: =VLOOKUP(L6,Asset_Allocation!$A$6:$L$8,3,FALSE) -> 0.6 | P6: =VLOOKUP(L6,Asset_Allocation!$A$6:$L$8,4,FALSE) -> 0.1 | Q6: =VLOOKUP(L6,Asset_Allocation!$A$6:$L$8,5,FALSE) -> 0.1 | R6: =$C$18*M6 -> 5999.9296 | S6: =E6-(Simulation!A6)+1 -> 1 | T6: =IF(S6>15,"Aggressive",IF(S6>10,"Growth",IF(S6>7,"Moderate",IF(S6>3,"Balanced","Conservative")))) -> Conservative | U6: =INDEX(Asset_Allocation!$C$16:$C$20,MATCH(T6,Asset_Allocation!$B$16:$B$20,0)) -> 0.25 | V6: =INDEX(Asset_Allocation!$D$16:$D$20,MATCH(T6,Asset_Allocation!$B$16:$B$20,0)) -> 0.6 | W6: =INDEX(Asset_Allocation!$E$16:$E$20,MATCH(T6,Asset_Allocation!$B$16:$B$20,0)) -> 0.1 | X6: =INDEX(Asset_Allocation!$F$16:$F$20,MATCH(T6,Asset_Allocation!$B$16:$B$20,0)) -> 0.05
A7: Vacation | B7: Aspirational | C7: Low | D7: 200000 | E7: 2 | F7: 0.06 | G7: =D7*(1+F7)^E7 -> 224720 | H7: 20000 | I7: 5000 | J7: 0.1 | K7: =G7/(1+J7)^E7 -> 185719.01 | L7: =IF(E7<=3,"Conservative",IF(E7<=10,"Moderate","Aggressive")) -> Conservative | M7: =G7/$G$14 -> 0.0021855414 | N7: =VLOOKUP(L7,Asset_Allocation!$A$6:$L$8,2,FALSE) -> 0.2 | O7: =VLOOKUP(L7,Asset_Allocation!$A$6:$L$8,3,FALSE) -> 0.6 | P7: =VLOOKUP(L7,Asset_Allocation!$A$6:$L$8,4,FALSE) -> 0.1 | Q7: =VLOOKUP(L7,Asset_Allocation!$A$6:$L$8,5,FALSE) -> 0.1 | R7: =$C$18*M7 -> 2543.9702 | S7: =E7-(Simulation!$A$6)+1 -> 2 | T7: =IF(S7>15,"Aggressive",IF(S7>10,"Growth",IF(S7>7,"Moderate",IF(S7>3,"Balanced","Conservative")))) -> Conservative | U7: =INDEX(Asset_Allocation!$C$16:$C$20,MATCH(T7,Asset_Allocation!$B$16:$B$20,0)) -> 0.25 | V7: =INDEX(Asset_Allocation!$D$16:$D$20,MATCH(T7,Asset_Allocation!$B$16:$B$20,0)) -> 0.6 | W7: =INDEX(Asset_Allocation!$E$16:$E$20,MATCH(T7,Asset_Allocation!$B$16:$B$20,0)) -> 0.1 | X7: =INDEX(Asset_Allocation!$F$16:$F$20,MATCH(T7,Asset_Allocation!$B$16:$B$20,0)) -> 0.05
A8: Car Down Payment | B8: Important | C8: Medium | D8: 500000 | E8: 3 | F8: 0.07 | G8: =D8*(1+F8)^E8 -> 612521.5 | H8: 50000 | I8: 10000 | J8: 0.11 | K8: =G8/(1+J8)^E8 -> 447870.44 | L8: =IF(E8<=3,"Conservative",IF(E8<=10,"Moderate","Aggressive")) -> Conservative | M8: =G8/$G$14 -> 0.0059571515 | N8: =VLOOKUP(L8,Asset_Allocation!$A$6:$L$8,2,FALSE) -> 0.2 | O8: =VLOOKUP(L8,Asset_Allocation!$A$6:$L$8,3,FALSE) -> 0.6 | P8: =VLOOKUP(L8,Asset_Allocation!$A$6:$L$8,4,FALSE) -> 0.1 | Q8: =VLOOKUP(L8,Asset_Allocation!$A$6:$L$8,5,FALSE) -> 0.1 | R8: =$C$18*M8 -> 6934.1243 | S8: =E8-(Simulation!$A$6)+1 -> 3 | T8: =IF(S8>15,"Aggressive",IF(S8>10,"Growth",IF(S8>7,"Moderate",IF(S8>3,"Balanced","Conservative")))) -> Conservative | U8: =INDEX(Asset_Allocation!$C$16:$C$20,MATCH(T8,Asset_Allocation!$B$16:$B$20,0)) -> 0.25 | V8: =INDEX(Asset_Allocation!$D$16:$D$20,MATCH(T8,Asset_Allocation!$B$16:$B$20,0)) -> 0.6 | W8: =INDEX(Asset_Allocation!$E$16:$E$20,MATCH(T8,Asset_Allocation!$B$16:$B$20,0)) -> 0.1 | X8: =INDEX(Asset_Allocation!$F$16:$F$20,MATCH(T8,Asset_Allocation!$B$16:$B$20,0)) -> 0.05
A9: Education Fund | B9: Important | C9: High | D9: 5000000 | E9: 15 | F9: 0.08 | G9: =D9*(1+F9)^E9 -> 15860846 | H9: 200000 | I9: 15000 | J9: 0.12 | K9: =G9/(1+J9)^E9 -> 2897717.2 | L9: =IF(E9<=3,"Conservative",IF(E9<=10,"Moderate","Aggressive")) -> Aggressive | M9: =G9/$G$14 -> 0.15425656 | N9: =VLOOKUP(L9,Asset_Allocation!$A$6:$L$8,2,FALSE) -> 0.8 | O9: =VLOOKUP(L9,Asset_Allocation!$A$6:$L$8,3,FALSE) -> 0.1 | P9: =VLOOKUP(L9,Asset_Allocation!$A$6:$L$8,4,FALSE) -> 0.05 | Q9: =VLOOKUP(L9,Asset_Allocation!$A$6:$L$8,5,FALSE) -> 0.05 | R9: =$C$18*M9 -> 179554.64 | S9: =E9-(Simulation!$A$6)+1 -> 15 | T9: =IF(S9>15,"Aggressive",IF(S9>10,"Growth",IF(S9>7,"Moderate",IF(S9>3,"Balanced","Conservative")))) -> Growth | U9: =INDEX(Asset_Allocation!$C$16:$C$20,MATCH(T9,Asset_Allocation!$B$16:$B$20,0)) -> 0.7 | V9: =INDEX(Asset_Allocation!$D$16:$D$20,MATCH(T9,Asset_Allocation!$B$16:$B$20,0)) -> 0.2 | W9: =INDEX(Asset_Allocation!$E$16:$E$20,MATCH(T9,Asset_Allocation!$B$16:$B$20,0)) -> 0.05 | X9: =INDEX(Asset_Allocation!$F$16:$F$20,MATCH(T9,Asset_Allocation!$B$16:$B$20,0)) -> 0.05
A10: Retirement | B10: Essential | C10: High | D10: 20000000 | E10: 20 | F10: 0.07 | G10: =D10*(1+F10)^E10 -> 77393689 | H10: 500000 | I10: 20000 | J10: 0.12 | K10: =G10/(1+J10)^E10 -> 8023153.4 | L10: =IF(E10<=3,"Conservative",IF(E10<=10,"Moderate","Aggressive")) -> Aggressive | M10: =G10/$G$14 -> 0.75270163 | N10: =VLOOKUP(L10,Asset_Allocation!$A$6:$L$8,2,FALSE) -> 0.8 | O10: =VLOOKUP(L10,Asset_Allocation!$A$6:$L$8,3,FALSE) -> 0.1 | P10: =VLOOKUP(L10,Asset_Allocation!$A$6:$L$8,4,FALSE) -> 0.05 | Q10: =VLOOKUP(L10,Asset_Allocation!$A$6:$L$8,5,FALSE) -> 0.05 | R10: =$C$18*M10 -> 876144.7 | S10: =E10-(Simulation!$A$6)+1 -> 20 | T10: =IF(S10>15,"Aggressive",IF(S10>10,"Growth",IF(S10>7,"Moderate",IF(S10>3,"Balanced","Conservative")))) -> Aggressive | U10: =INDEX(Asset_Allocation!$C$16:$C$20,MATCH(T10,Asset_Allocation!$B$16:$B$20,0)) -> 0.8 | V10: =INDEX(Asset_Allocation!$D$16:$D$20,MATCH(T10,Asset_Allocation!$B$16:$B$20,0)) -> 0.1 | W10: =INDEX(Asset_Allocation!$E$16:$E$20,MATCH(T10,Asset_Allocation!$B$16:$B$20,0)) -> 0.05 | X10: =INDEX(Asset_Allocation!$F$16:$F$20,MATCH(T10,Asset_Allocation!$B$16:$B$20,0)) -> 0.05
A11: Marriage | B11: Important | C11: Medium | D11: 3000000 | E11: 10 | F11: 0.07 | G11: =D11*(1+F11)^E11 -> 5901454.1 | H11: 100000 | I11: 10000 | J11: 0.11 | K11: =G11/(1+J11)^E11 -> 2078400.5 | L11: =IF(E11<=3,"Conservative",IF(E11<=10,"Moderate","Aggressive")) -> Moderate | M11: =G11/$G$14 -> 0.057395301 | N11: =VLOOKUP(L11,Asset_Allocation!$A$6:$L$8,2,FALSE) -> 0.5 | O11: =VLOOKUP(L11,Asset_Allocation!$A$6:$L$8,3,FALSE) -> 0.3 | P11: =VLOOKUP(L11,Asset_Allocation!$A$6:$L$8,4,FALSE) -> 0.1 | Q11: =VLOOKUP(L11,Asset_Allocation!$A$6:$L$8,5,FALSE) -> 0.1 | R11: =$C$18*M11 -> 66808.13 | S11: =E11-(Simulation!$A$6)+1 -> 10 | T11: =IF(S11>15,"Aggressive",IF(S11>10,"Growth",IF(S11>7,"Moderate",IF(S11>3,"Balanced","Conservative")))) -> Moderate | U11: =INDEX(Asset_Allocation!$C$16:$C$20,MATCH(T11,Asset_Allocation!$B$16:$B$20,0)) -> 0.6 | V11: =INDEX(Asset_Allocation!$D$16:$D$20,MATCH(T11,Asset_Allocation!$B$16:$B$20,0)) -> 0.25 | W11: =INDEX(Asset_Allocation!$E$16:$E$20,MATCH(T11,Asset_Allocation!$B$16:$B$20,0)) -> 0.1 | X11: =INDEX(Asset_Allocation!$F$16:$F$20,MATCH(T11,Asset_Allocation!$B$16:$B$20,0)) -> 0.05
A12: Home Upgrade | B12: Important | C12: Medium | D12: 1000000 | E12: 5 | F12: 0.07 | G12: =D12*(1+F12)^E12 -> 1402551.7 | H12: 100000 | I12: 12000 | J12: 0.1 | K12: =G12/(1+J12)^E12 -> 870874.28 | L12: =IF(E12<=3,"Conservative",IF(E12<=10,"Moderate","Aggressive")) -> Moderate | M12: =G12/$G$14 -> 0.013640685 | N12: =VLOOKUP(L12,Asset_Allocation!$A$6:$L$8,2,FALSE) -> 0.5 | O12: =VLOOKUP(L12,Asset_Allocation!$A$6:$L$8,3,FALSE) -> 0.3 | P12: =VLOOKUP(L12,Asset_Allocation!$A$6:$L$8,4,FALSE) -> 0.1 | Q12: =VLOOKUP(L12,Asset_Allocation!$A$6:$L$8,5,FALSE) -> 0.1 | R12: =$C$18*M12 -> 15877.758 | S12: =E12-(Simulation!$A$6)+1 -> 5 | T12: =IF(S12>15,"Aggressive",IF(S12>10,"Growth",IF(S12>7,"Moderate",IF(S12>3,"Balanced","Conservative")))) -> Balanced | U12: =INDEX(Asset_Allocation!$C$16:$C$20,MATCH(T12,Asset_Allocation!$B$16:$B$20,0)) -> 0.45 | V12: =INDEX(Asset_Allocation!$D$16:$D$20,MATCH(T12,Asset_Allocation!$B$16:$B$20,0)) -> 0.4 | W12: =INDEX(Asset_Allocation!$E$16:$E$20,MATCH(T12,Asset_Allocation!$B$16:$B$20,0)) -> 0.1 | X12: =INDEX(Asset_Allocation!$F$16:$F$20,MATCH(T12,Asset_Allocation!$B$16:$B$20,0)) -> 0.05
A13: Philanthropy | B13: Aspirational | C13: Low | D13: 500000 | E13: 10 | F13: 0.06 | G13: =D13*(1+F13)^E13 -> 895423.85 | H13: 50000 | I13: 5000 | J13: 0.09 | K13: =G13/(1+J13)^E13 -> 378236.71 | L13: =IF(E13<=3,"Conservative",IF(E13<=10,"Moderate","Aggressive")) -> Moderate | M13: =G13/$G$14 -> 0.0087085523 | N13: =VLOOKUP(L13,Asset_Allocation!$A$6:$L$8,2,FALSE) -> 0.5 | O13: =VLOOKUP(L13,Asset_Allocation!$A$6:$L$8,3,FALSE) -> 0.3 | P13: =VLOOKUP(L13,Asset_Allocation!$A$6:$L$8,4,FALSE) -> 0.1 | Q13: =VLOOKUP(L13,Asset_Allocation!$A$6:$L$8,5,FALSE) -> 0.1 | R13: =$C$18*M13 -> 10136.755 | S13: =E13-(Simulation!$A$6)+1 -> 10 | T13: =IF(S13>15,"Aggressive",IF(S13>10,"Growth",IF(S13>7,"Moderate",IF(S13>3,"Balanced","Conservative")))) -> Moderate | U13: =INDEX(Asset_Allocation!$C$16:$C$20,MATCH(T13,Asset_Allocation!$B$16:$B$20,0)) -> 0.6 | V13: =INDEX(Asset_Allocation!$D$16:$D$20,MATCH(T13,Asset_Allocation!$B$16:$B$20,0)) -> 0.25 | W13: =INDEX(Asset_Allocation!$E$16:$E$20,MATCH(T13,Asset_Allocation!$B$16:$B$20,0)) -> 0.1 | X13: =INDEX(Asset_Allocation!$F$16:$F$20,MATCH(T13,Asset_Allocation!$B$16:$B$20,0)) -> 0.05
D14: =SUM(D6:D13) -> 30700000 | G14: =SUM(G6:G13) -> 1.0282121e+08 | H14: =SUM(H6:H13) -> 1120000 | I14: =SUM(I6:I13) -> 97000
B17: Monthly SIP | C17: 97000
B18: Annual SIP | C18: =C17*12 -> 1164000

Sheet Asset_Allocation
B3: Asset_Allocation
A5: Risk Profile | B5: Equity % | C5: Debt % | D5: Precious Metals % | E5: Alternatives % | F5: Large Cap % | G5: Mid Cap % | H5: Small Cap % | I5: Govt Bonds % | J5: Corp Bonds % | K5: Domestic % | L5: International %
A6: Conservative | B6: 0.2 | C6: 0.6 | D6: 0.1 | E6: 0.1 | F6: 0.5 | G6: 0.3 | H6: 0.2 | I6: 0.7 | J6: 0.3 | K6: 0.8 | L6: 0.2
A7: Moderate | B7: 0.5 | C7: 0.3 | D7: 0.1 | E7: 0.1 | F7: 0.4 | G7: 0.35 | H7: 0.25 | I7: 0.6 | J7: 0.4 | K7: 0.7 | L7: 0.3
A8: Aggressive | B8: 0.8 | C8: 0.1 | D8: 0.05 | E8: 0.05 | F8: 0.3 | G8: 0.4 | H8: 0.3 | I8: 0.5 | J8: 0.5 | K8: 0.6 | L8: 0.4
B12: Glide Path Table
A15: Years Left | B15: Risk Stage | C15: Equity% | D15: Debt% | E15: Precious Metals % | F15: Alternatives %
A16: >15 | B16: Aggressive | C16: 0.8 | D16: 0.1 | E16: 0.05 | F16: 0.05
A17: 10 to 15 | B17: Growth | C17: 0.7 | D17: 0.2 | E17: 0.05 | F17: 0.05
A18: 7 to 10 | B18: Moderate | C18: 0.6 | D18: 0.25 | E18: 0.1 | F18: 0.05
A19: 4 to 7 | B19: Balanced | C19: 0.45 | D19: 0.4 | E19: 0.1 | F19: 0.05
A20: 1 to 3 | B20: Conservative | C20: 0.25 | D20: 0.6 | E20: 0.1 | F20: 0.05

Sheet Combined_Portfolio
C3: Combined_Portfolio
Q4: Actual - Target
A5: Goal | B5: Target FV | C5: Weight | D5: Equity % | E5: Debt % | F5: Precious Metals % | G5: Alternatives % | H5: Goal SIP | I5: Years Left | J5: Target Equity % | K5: Target Debt % | L5: Target Precious Metals % | M5: Target Alternatives % | N5: Equity Drift | O5: Debt Drift | P5: Precious Metals Drift | Q5: Alternatives Drift | R5: Equity Flag | S5: Debt Flag | T5: Precious Metals Flag | U5: Alternatives Flag | V5: Overall Portfolio Rebalance Flag | W5: Rebalance Reason
A6: ='Goals Input'!A6 -> Emergency Fund | B6: ='Goals Input'!G6 -> 530000 | C6: =B6/$B$14 -> 0.0051545787 | D6: =VLOOKUP('Goals Input'!L6,Asset_Allocation!A6:L8,2,FALSE) -> 0.2 | E6: =VLOOKUP('Goals Input'!L6,Asset_Allocation!A6:L8,3,FALSE) -> 0.6 | F6: =VLOOKUP('Goals Input'!L6,Asset_Allocation!A6:L8,4,FALSE) -> 0.1 | G6: =VLOOKUP('Goals Input'!L6,Asset_Allocation!A6:L8,5,FALSE) -> 0.1 | H6: =$B$28*C6 -> 5999.9296 | I6: =MAX(0,'Goals Input'!S6-Simulation!$A$6+1) -> 1 | J6: =IF(I6>15,80%,IF(I6>10,70%,IF(I6>7,60%,IF(I6>3,45%,25%)))) -> 0.25 | K6: =IF(I6>15,10%,IF(I6>10,20%,IF(I6>7,25%,IF(I6>3,40%,60%)))) -> 0.6 | L6: =IF(I6>15,5%,IF(I6>10,5%,IF(I6>7,10%,IF(I6>3,10%,10%)))) -> 0.1 | M6: =IF(I6>15,5%,IF(I6>10,5%,IF(I6>7,5%,IF(I6>3,5%,5%)))) -> 0.05 | N6: =D6-J6 -> -0.05 | O6: =E6-K6 -> 0 | P6: =F6-L6 -> 0 | Q6: =G6-M6 -> 0.05 | R6: =IF(ABS(N6)>5%,"Rebalance","Hold") -> Hold | S6: =IF(ABS(O6)>5%,"Rebalance","Hold") -> Hold | T6: =IF(ABS(P6)>5%,"Rebalance","Hold") -> Hold | U6: =IF(ABS(Q6)>5%,"Rebalance","Hold") -> Hold | V6: =IF(COUNTIF(R6:U6,"Rebalance")>0,"Rebalance Portfolio","Hold") -> Hold | W6: =IF(COUNTIF(R8:U8,"Rebalance")=0, "Within Threshold", _xlfn.TEXTJOIN(", ",TRUE, IF(R8="Rebalance","Equity",""), IF(S8="Rebalance","Debt",""), IF(T8="Rebalance","Gold",""), IF(U8="Rebalance","Alternative","") )) -> Within Threshold
A7: ='Goals Input'!A7 -> Vacation | B7: ='Goals Input'!G7 -> 224720 | C7: =B7/$B$14 -> 0.0021855414 | D7: =VLOOKUP('Goals Input'!L7,Asset_Allocation!A6:L8,2,FALSE) -> 0.2 | E7: =VLOOKUP('Goals Input'!L7,Asset_Allocation!A6:L8,3,FALSE) -> 0.6 | F7: =VLOOKUP('Goals Input'!L7,Asset_Allocation!A6:L8,4,FALSE) -> 0.1 | G7: =VLOOKUP('Goals Input'!L7,Asset_Allocation!A6:L8,5,FALSE) -> 0.1 | H7: =$B$28*C7 -> 2543.9702 | I7: =MAX(0,'Goals Input'!S7-Simulation!$A$6+1) -> 2 | J7: =IF(I7>15,80%,IF(I7>10,70%,IF(I7>7,60%,IF(I7>3,45%,25%)))) -> 0.25 | K7: =IF(I7>15,10%,IF(I7>10,20%,IF(I7>7,25%,IF(I7>3,40%,60%)))) -> 0.6 | L7: =IF(I7>15,5%,IF(I7>10,5%,IF(I7>7,10%,IF(I7>3,10%,10%)))) -> 0.1 | M7: =IF(I7>15,5%,IF(I7>10,5%,IF(I7>7,5%,IF(I7>3,5%,5%)))) -> 0.05 | N7: =D7-J7 -> -0.05 | O7: =E7-K7 -> 0 | P7: =F7-L7 -> 0 | Q7: =G7-M7 -> 0.05 | R7: =IF(ABS(N7)>5%,"Rebalance","Hold") -> Hold | S7: =IF(ABS(O7)>5%,"Rebalance","Hold") -> Hold | T7: =IF(ABS(P7)>5%,"Rebalance","Hold") -> Hold | U7: =IF(ABS(Q7)>5%,"Rebalance","Hold") -> Hold | V7: =IF(COUNTIF(R7:U7,"Rebalance")>0,"Rebalance Portfolio","Hold") -> Hold | W7: =IF(COUNTIF(R9:U9,"Rebalance")=0, "Within Threshold", _xlfn.TEXTJOIN(", ",TRUE, IF(R9="Rebalance","Equity",""), IF(S9="Rebalance","Debt",""), IF(T9="Rebalance","Gold",""), IF(U9="Rebalance","Alternative","") )) -> Equity, Debt
A8: ='Goals Input'!A8 -> Car Down Payment | B8: ='Goals Input'!G8 -> 612521.5 | C8: =B8/$B$14 -> 0.0059571515 | D8: =VLOOKUP('Goals Input'!L8,Asset_Allocation!A6:L8,2,FALSE) -> 0.2 | E8: =VLOOKUP('Goals Input'!L8,Asset_Allocation!A6:L80,3,FALSE) -> 0.6 | F8: =VLOOKUP('Goals Input'!L8,Asset_Allocation!A6:L8,4,FALSE) -> 0.1 | G8: =VLOOKUP('Goals Input'!L8,Asset_Allocation!A6:L8,5,FALSE) -> 0.1 | H8: =$B$28*C8 -> 6934.1243 | I8: =MAX(0,'Goals Input'!S8-Simulation!$A$6+1) -> 3 | J8: =IF(I8>15,80%,IF(I8>10,70%,IF(I8>7,60%,IF(I8>3,45%,25%)))) -> 0.25 | K8: =IF(I8>15,10%,IF(I8>10,20%,IF(I8>7,25%,IF(I8>3,40%,60%)))) -> 0.6 | L8: =IF(I8>15,5%,IF(I8>10,5%,IF(I8>7,10%,IF(I8>3,10%,10%)))) -> 0.1 | M8: =IF(I8>15,5%,IF(I8>10,5%,IF(I8>7,5%,IF(I8>3,5%,5%)))) -> 0.05 | N8: =D8-J8 -> -0.05 | O8: =E8-K8 -> 0 | P8: =F8-L8 -> 0 | Q8: =G8-M8 -> 0.05 | R8: =IF(ABS(N8)>5%,"Rebalance","Hold") -> Hold | S8: =IF(ABS(O8)>5%,"Rebalance","Hold") -> Hold | T8: =IF(ABS(P8)>5%,"Rebalance","Hold") -> Hold | U8: =IF(ABS(Q8)>5%,"Rebalance","Hold") -> Hold | V8: =IF(COUNTIF(R8:U8,"Rebalance")>0,"Rebalance Portfolio","Hold") -> Hold | W8: =IF(COUNTIF(R10:U10,"Rebalance")=0, "Within Threshold", _xlfn.TEXTJOIN(", ",TRUE, IF(R10="Rebalance","Equity",""), IF(S10="Rebalance","Debt",""), IF(T10="Rebalance","Gold",""), IF(U10="Rebalance","Alternative","") )) -> Within Threshold
A9: ='Goals Input'!A9 -> Education Fund | B9: ='Goals Input'!G9 -> 15860846 | C9: =B9/$B$14 -> 0.15425656 | D9: =VLOOKUP('Goals Input'!L9,Asset_Allocation!A6:L8,2,FALSE) -> 0.8 | E9: =VLOOKUP('Goals Input'!L9,Asset_Allocation!A6:L8,3,FALSE) -> 0.1 | F9: =VLOOKUP('Goals Input'!L9,Asset_Allocation!A6:L8,4,FALSE) -> 0.05 | G9: =VLOOKUP('Goals Input'!L9,Asset_Allocation!A6:L8,5,FALSE) -> 0.05 | H9: =$B$28*C9 -> 179554.64 | I9: =MAX(0,'Goals Input'!S9-Simulation!$A$6+1) -> 15 | J9: =IF(I9>15,80%,IF(I9>10,70%,IF(I9>7,60%,IF(I9>3,45%,25%)))) -> 0.7 | K9: =IF(I9>15,10%,IF(I9>10,20%,IF(I9>7,25%,IF(I9>3,40%,60%)))) -> 0.2 | L9: =IF(I9>15,5%,IF(I9>10,5%,IF(I9>7,10%,IF(I9>3,10%,10%)))) -> 0.05 | M9: =IF(I9>15,5%,IF(I9>10,5%,IF(I9>7,5%,IF(I9>3,5%,5%)))) -> 0.05 | N9: =D9-J9 -> 0.1 | O9: =E9-K9 -> -0.1 | P9: =F9-L9 -> 0 | Q9: =G9-M9 -> 0 | R9: =IF(ABS(N9)>5%,"Rebalance","Hold") -> Rebalance | S9: =IF(ABS(O9)>5%,"Rebalance","Hold") -> Rebalance | T9: =IF(ABS(P9)>5%,"Rebalance","Hold") -> Hold | U9: =IF(ABS(Q9)>5%,"Rebalance","Hold") -> Hold | V9: =IF(COUNTIF(R9:U9,"Rebalance")>0,"Rebalance Portfolio","Hold") -> Rebalance Portfolio | W9: =IF(COUNTIF(R11:U11,"Rebalance")=0, "Within Threshold", _xlfn.TEXTJOIN(", ",TRUE, IF(R11="Rebalance","Equity",""), IF(S11="Rebalance","Debt",""), IF(T11="Rebalance","Gold",""), IF(U11="Rebalance","Alternative","") )) -> Equity
A10: ='Goals Input'!A10 -> Retirement | B10: ='Goals Input'!G10 -> 77393689 | C10: =B10/$B$14 -> 0.75270163 | D10: =VLOOKUP('Goals Input'!L10,Asset_Allocation!A6:L8,2,FALSE) -> 0.8 | E10: =VLOOKUP('Goals Input'!L10,Asset_Allocation!A6:L8,3,FALSE) -> 0.1 | F10: =VLOOKUP('Goals Input'!L10,Asset_Allocation!A6:L8,4,FALSE) -> 0.05 | G10: =VLOOKUP('Goals Input'!L10,Asset_Allocation!A6:L8,5,FALSE) -> 0.05 | H10: =$B$28*C10 -> 876144.7 | I10: =MAX(0,'Goals Input'!S10-Simulation!$A$6+1) -> 20 | J10: =IF(I10>15,80%,IF(I10>10,70%,IF(I10>7,60%,IF(I10>3,45%,25%)))) -> 0.8 | K10: =IF(I10>15,10%,IF(I10>10,20%,IF(I10>7,25%,IF(I10>3,40%,60%)))) -> 0.1 | L10: =IF(I10>15,5%,IF(I10>10,5%,IF(I10>7,10%,IF(I10>3,10%,10%)))) -> 0.05 | M10: =IF(I10>15,5%,IF(I10>10,5%,IF(I10>7,5%,IF(I10>3,5%,5%)))) -> 0.05 | N10: =D10-J10 -> 0 | O10: =E10-K10 -> 0 | P10: =F10-L10 -> 0 | Q10: =G10-M10 -> 0 | R10: =IF(ABS(N10)>5%,"Rebalance","Hold") -> Hold | S10: =IF(ABS(O10)>5%,"Rebalance","Hold") -> Hold | T10: =IF(ABS(P10)>5%,"Rebalance","Hold") -> Hold | U10: =IF(ABS(Q10)>5%,"Rebalance","Hold") -> Hold | V10: =IF(COUNTIF(R10:U10,"Rebalance")>0,"Rebalance Portfolio","Hold") -> Hold | W10: =IF(COUNTIF(R12:U12,"Rebalance")=0, "Within Threshold", _xlfn.TEXTJOIN(", ",TRUE, IF(R12="Rebalance","Equity",""), IF(S12="Rebalance","Debt",""), IF(T12="Rebalance","Gold",""), IF(U12="Rebalance","Alternative","") )) -> Debt
A11: ='Goals Input'!A11 -> Marriage | B11: ='Goals Input'!G11 -> 5901454.1 | C11: =B11/$B$14 -> 0.057395301 | D11: =VLOOKUP('Goals Input'!L11,Asset_Allocation!A6:L8,2,FALSE) -> 0.5 | E11: =VLOOKUP('Goals Input'!L11,Asset_Allocation!A6:L8,3,FALSE) -> 0.3 | F11: =VLOOKUP('Goals Input'!L11,Asset_Allocation!A6:L8,4,FALSE) -> 0.1 | G11: =VLOOKUP('Goals Input'!L11,Asset_Allocation!A6:L8,5,FALSE) -> 0.1 | H11: =$B$28*C11 -> 66808.13 | I11: =MAX(0,'Goals Input'!S11-Simulation!$A$6+1) -> 10 | J11: =IF(I11>15,80%,IF(I11>10,70%,IF(I11>7,60%,IF(I11>3,45%,25%)))) -> 0.6 | K11: =IF(I11>15,10%,IF(I11>10,20%,IF(I11>7,25%,IF(I11>3,40%,60%)))) -> 0.25 | L11: =IF(I11>15,5%,IF(I11>10,5%,IF(I11>7,10%,IF(I11>3,10%,10%)))) -> 0.1 | M11: =IF(I11>15,5%,IF(I11>10,5%,IF(I11>7,5%,IF(I11>3,5%,5%)))) -> 0.05 | N11: =D11-J11 -> -0.1 | O11: =E11-K11 -> 0.05 | P11: =F11-L11 -> 0 | Q11: =G11-M11 -> 0.05 | R11: =IF(ABS(N11)>5%,"Rebalance","Hold") -> Rebalance | S11: =IF(ABS(O11)>5%,"Rebalance","Hold") -> Hold | T11: =IF(ABS(P11)>5%,"Rebalance","Hold") -> Hold | U11: =IF(ABS(Q11)>5%,"Rebalance","Hold") -> Hold | V11: =IF(COUNTIF(R11:U11,"Rebalance")>0,"Rebalance Portfolio","Hold") -> Rebalance Portfolio | W11: =IF(COUNTIF(R13:U13,"Rebalance")=0, "Within Threshold", _xlfn.TEXTJOIN(", ",TRUE, IF(R13="Rebalance","Equity",""), IF(S13="Rebalance","Debt",""), IF(T13="Rebalance","Gold",""), IF(U13="Rebalance","Alternative","") )) -> Equity
A12: ='Goals Input'!A12 -> Home Upgrade | B12: ='Goals Input'!G12 -> 1402551.7 | C12: =B12/$B$14 -> 0.013640685 | D12: =VLOOKUP('Goals Input'!L12,Asset_Allocation!A6:L8,2,FALSE) -> 0.5 | E12: =VLOOKUP('Goals Input'!L12,Asset_Allocation!A6:L8,3,FALSE) -> 0.3 | F12: =VLOOKUP('Goals Input'!L12,Asset_Allocation!A6:L8,4,FALSE) -> 0.1 | G12: =VLOOKUP('Goals Input'!L12,Asset_Allocation!A6:L8,5,FALSE) -> 0.1 | H12: =$B$28*C12 -> 15877.758 | I12: =MAX(0,'Goals Input'!S12-Simulation!$A$6+1) -> 5 | J12: =IF(I12>15,80%,IF(I12>10,70%,IF(I12>7,60%,IF(I12>3,45%,25%)))) -> 0.45 | K12: =IF(I12>15,10%,IF(I12>10,20%,IF(I12>7,25%,IF(I12>3,40%,60%)))) -> 0.4 | L12: =IF(I12>15,5%,IF(I12>10,5%,IF(I12>7,10%,IF(I12>3,10%,10%)))) -> 0.1 | M12: =IF(I12>15,5%,IF(I12>10,5%,IF(I12>7,5%,IF(I12>3,5%,5%)))) -> 0.05 | N12: =D12-J12 -> 0.05 | O12: =E12-K12 -> -0.1 | P12: =F12-L12 -> 0 | Q12: =G12-M12 -> 0.05 | R12: =IF(ABS(N12)>5%,"Rebalance","Hold") -> Hold | S12: =IF(ABS(O12)>5%,"Rebalance","Hold") -> Rebalance | T12: =IF(ABS(P12)>5%,"Rebalance","Hold") -> Hold | U12: =IF(ABS(Q12)>5%,"Rebalance","Hold") -> Hold | V12: =IF(COUNTIF(R12:U12,"Rebalance")>0,"Rebalance Portfolio","Hold") -> Rebalance Portfolio | W12: =IF(COUNTIF(R14:U14,"Rebalance")=0, "Within Threshold", _xlfn.TEXTJOIN(", ",TRUE, IF(R14="Rebalance","Equity",""), IF(S14="Rebalance","Debt",""), IF(T14="Rebalance","Gold",""), IF(U14="Rebalance","Alternative","") )) -> Within Threshold
A13: ='Goals Input'!A13 -> Philanthropy | B13: ='Goals Input'!G13 -> 895423.85 | C13: =B13/$B$14 -> 0.0087085523 | D13: =VLOOKUP('Goals Input'!L13,Asset_Allocation!A6:L8,2,FALSE) -> 0.5 | E13: =VLOOKUP('Goals Input'!L13,Asset_Allocation!A6:L8,3,FALSE) -> 0.3 | F13: =VLOOKUP('Goals Input'!L13,Asset_Allocation!A6:L8,4,FALSE) -> 0.1 | G13: =VLOOKUP('Goals Input'!L13,Asset_Allocation!A6:L8,5,FALSE) -> 0.1 | H13: =$B$28*C13 -> 10136.755 | I13: =MAX(0,'Goals Input'!S13-Simulation!$A$6+1) -> 10 | J13: =IF(I13>15,80%,IF(I13>10,70%,IF(I13>7,60%,IF(I13>3,45%,25%)))) -> 0.6 | K13: =IF(I13>15,10%,IF(I13>10,20%,IF(I13>7,25%,IF(I13>3,40%,60%)))) -> 0.25 | L13: =IF(I13>15,5%,IF(I13>10,5%,IF(I13>7,10%,IF(I13>3,10%,10%)))) -> 0.1 | M13: =IF(I13>15,5%,IF(I13>10,5%,IF(I13>7,5%,IF(I13>3,5%,5%)))) -> 0.05 | N13: =D13-J13 -> -0.1 | O13: =E13-K13 -> 0.05 | P13: =F13-L13 -> 0 | Q13: =G13-M13 -> 0.05 | R13: =IF(ABS(N13)>5%,"Rebalance","Hold") -> Rebalance | S13: =IF(ABS(O13)>5%,"Rebalance","Hold") -> Hold | T13: =IF(ABS(P13)>5%,"Rebalance","Hold") -> Hold | U13: =IF(ABS(Q13)>5%,"Rebalance","Hold") -> Hold | V13: =IF(COUNTIF(R13:U13,"Rebalance")>0,"Rebalance Portfolio","Hold") -> Rebalance Portfolio | W13: =IF(COUNTIF(R15:U15,"Rebalance")=0, "Within Threshold", _xlfn.TEXTJOIN(", ",TRUE, IF(R15="Rebalance","Equity",""), IF(S15="Rebalance","Debt",""), IF(T15="Rebalance","Gold",""), IF(U15="Rebalance","Alternative","") )) -> Within Threshold
A14: Total | B14: =SUM(B6:B13) -> 1.0282121e+08 | C14: =B14/$B$14 -> 1
A17: Final Portfolio Calculation
A19: Asset class | B19: Actual % | C19: Target % | D19: Drift | E19: Rebalance Flag
A20: Equity | B20: =SUMPRODUCT(C6:C13,D6:D13) -> 0.76809828 | C20: =SUMPRODUCT(C6:C13,J6:J13) -> 0.75926583 | D20: =B20-C20 -> 0.0088324414 | E20: =IF(ABS(D20)>5%,"Rebalance","Hold") -> Hold
A21: Dedt | B21: =SUMPRODUCT(C6:C13,E6:E13) -> 0.12259754 | C21: =SUMPRODUCT(C6:C13,K6:K13) -> 0.13608208 | D21: =B21-C21 -> -0.013484532 | E21: =IF(ABS(D21)>5%,"Rebalance","Hold") -> Hold
A22: Precious Metals | B22: =SUMPRODUCT(C6:C13,F6:F13) -> 0.054652091 | C22: =SUMPRODUCT(C6:C13,L6:L13) -> 0.054652091 | D22: =B22-C22 -> 0 | E22: =IF(ABS(D22)>5%,"Rebalance","Hold") -> Hold
A23: Alternatives | B23: =SUMPRODUCT(C6:C13,G6:G13) -> 0.054652091 | C23: =SUMPRODUCT(C6:C13,M6:M13) -> 0.05 | D23: =B23-C23 -> 0.0046520905 | E23: =IF(ABS(D23)>5%,"Rebalance","Hold") -> Hold
B24: =SUM(B20:B23) -> 1 | C24: =SUM(C20:C23) -> 1
B27: Total SIP ANNUAL
B28: 1164000

Sheet Simulation
B3: Simulation | N3: Hepler table
B4: Combined portfolio Simulation
A5: Year | B5: Portfolio Value | C5: Equity Return | D5: Debt Return | E5: Metals Return | F5: Alt Return | G5: Portfolio Return | H5: SIP (Yearly) | I5: New Value | J5: Funded Ratio | L5: Years | M5: Avg Years Left | N5: Equity % | O5: Debt % | P5: Metals % | Q5: Alit %
A6: 1 | B6: =SUM('Goals Input'!H6:H13) -> 1120000 | C6: 0.08 | D6: 0.05 | E6: -0.01 | F6: 0.08 | G6: =SUMPRODUCT(N6:Q6,C6:F6) -> 0.0725 | H6: =Cash_Flow!D23 -> 1164000 | I6: =(B6*(1+G6))+H6 -> 2365200 | J6: =I6 / Combined_Portfolio!B14 -> 0.023003037 | L6: =A6 -> 1 | M6: {=IFERROR(SUMPRODUCT(Combined_Portfolio!$C$6:$C$13,(('Goals Input'!$E$6:$E$13-L6+1)*(('Goals Input'!$E$6:$E$13-L6+1>0))))/SUMPRODUCT(Combined_Portfolio!$C$6:$C$13,--(('Goals Input'!$E$6:$E$13-L6+1)>0)),0)} -> 18.12452 | N6: =IF(M6>15,80%,IF(M6>10,70%,IF(M6>7,60%,IF(M6>3,45%,25%)))) -> 0.8 | O6: =IF(M6>15,10%,IF(M6>10,20%,IF(M6>7,25%,IF(M6>3,40%,60%)))) -> 0.1 | P6: =IF(M6>15,5%,IF(M6>10,5%,IF(M6>7,10%,IF(M6>3,10%,10%)))) -> 0.05 | Q6: =5% -> 0.05
A7: 2 | B7: =I6 -> 2365200 | C7: -0.02 | D7: 0.07 | E7: 0.07 | F7: 0.1 | G7: =SUMPRODUCT(N7:Q7,C7:F7) -> -0.0005 | H7: =Cash_Flow!D24 -> 1222200 | I7: =(B7*(1+G7))+H7 -> 3586217.4 | J7: =I7/Combined_Portfolio!B14 -> 0.034878188 | L7: =A7 -> 2 | M7: {=IFERROR(SUMPRODUCT(Combined_Portfolio!$C$6:$C$13,(('Goals Input'!$E$6:$E$13-L7+1)*(('Goals Input'!$E$6:$E$13-L7+1>0))))/SUMPRODUCT(Combined_Portfolio!$C$6:$C$13,--(('Goals Input'!$E$6:$E$13-L7+1)>0)),0)} -> 17.213247 | N7: =IF(M7>15,80%,IF(M7>10,70%,IF(M7>7,60%,IF(M7>3,45%,25%)))) -> 0.8 | O7: =IF(M7>15,10%,IF(M7>10,20%,IF(M7>7,25%,IF(M7>3,40%,60%)))) -> 0.1 | P7: =IF(M7>15,5%,IF(M7>10,5%,IF(M7>7,10%,IF(M7>3,10%,10%)))) -> 0.05 | Q7: =5% -> 0.05
A8: 3 | B8: =I7 -> 3586217.4 | C8: -0.1 | D8: 0.08 | E8: 0.12 | F8: 0.09 | G8: =SUMPRODUCT(N8:Q8,C8:F8) -> -0.0615 | H8: =Cash_Flow!D25 -> 1283310 | I8: =(B8*(1+G8))+H8 -> 4648975 | J8: =I8/Combined_Portfolio!B14 -> 0.045214166 | L8: =A8 -> 3 | M8: {=IFERROR(SUMPRODUCT(Combined_Portfolio!$C$6:$C$13,(('Goals Input'!$E$6:$E$13-L8+1)*(('Goals Input'!$E$6:$E$13-L8+1>0))))/SUMPRODUCT(Combined_Portfolio!$C$6:$C$13,--(('Goals Input'!$E$6:$E$13-L8+1)>0)),0)} -> 16.248944 | N8: =IF(M8>15,80%,IF(M8>10,70%,IF(M8>7,60%,IF(M8>3,45%,25%)))) -> 0.8 | O8: =IF(M8>15,10%,IF(M8>10,20%,IF(M8>7,25%,IF(M8>3,40%,60%)))) -> 0.1 | P8: =IF(M8>15,5%,IF(M8>10,5%,IF(M8>7,10%,IF(M8>3,10%,10%)))) -> 0.05 | Q8: =5% -> 0.05
A9: 4 | B9: =I8 -> 4648975 | C9: 0.09 | D9: 0.07 | E9: -0.04 | F9: 0.1 | G9: =SUMPRODUCT(N9:Q9,C9:F9) -> 0.082 | H9: =Cash_Flow!D26 -> 1347475.5 | I9: =(B9*(1+G9))+H9 -> 6377666.5 | J9: =I9/Combined_Portfolio!B14 -> 0.062026762 | L9: =A9 -> 4 | M9: {=IFERROR(SUMPRODUCT(Combined_Portfolio!$C$6:$C$13,(('Goals Input'!$E$6:$E$13-L9+1)*(('Goals Input'!$E$6:$E$13-L9+1>0))))/SUMPRODUCT(Combined_Portfolio!$C$6:$C$13,--(('Goals Input'!$E$6:$E$13-L9+1)>0)),0)} -> 15.341008 | N9: =IF(M9>15,80%,IF(M9>10,70%,IF(M9>7,60%,IF(M9>3,45%,25%)))) -> 0.8 | O9: =IF(M9>15,10%,IF(M9>10,20%,IF(M9>7,25%,IF(M9>3,40%,60%)))) -> 0.1 | P9: =IF(M9>15,5%,IF(M9>10,5%,IF(M9>7,10%,IF(M9>3,10%,10%)))) -> 0.05 | Q9: =5% -> 0.05
A10: 5 | B10: =I9 -> 6377666.5 | C10: 0.05 | D10: 0.08 | E10: 0.05 | F10: 0.1 | G10: =SUMPRODUCT(N10:Q10,C10:F10) -> 0.0585 | H10: =Cash_Flow!D27 -> 1414849.3 | I10: =(B10*(1+G10))+H10 -> 8165609.2 | J10: =I10/Combined_Portfolio!B14 -> 0.079415614 | L10: =A10 -> 5 | M10: {=IFERROR(SUMPRODUCT(Combined_Portfolio!$C$6:$C$13,(('Goals Input'!$E$6:$E$13-L10+1)*(('Goals Input'!$E$6:$E$13-L10+1>0))))/SUMPRODUCT(Combined_Portfolio!$C$6:$C$13,--(('Goals Input'!$E$6:$E$13-L10+1)>0)),0)} -> 14.341008 | N10: =IF(M10>15,80%,IF(M10>10,70%,IF(M10>7,60%,IF(M10>3,45%,25%)))) -> 0.7 | O10: =IF(M10>15,10%,IF(M10>10,20%,IF(M10>7,25%,IF(M10>3,40%,60%)))) -> 0.2 | P10: =IF(M10>15,5%,IF(M10>10,5%,IF(M10>7,10%,IF(M10>3,10%,10%)))) -> 0.05 | Q10: =5% -> 0.05
A11: 6 | B11: =I10 -> 8165609.2 | C11: 0.01 | D11: 0.08 | E11: 0.12 | F11: 0.11 | G11: =SUMPRODUCT(N11:Q11,C11:F11) -> 0.0345 | H11: =Cash_Flow!D28 -> 1485591.7 | I11: =(B11*(1+G11))+H11 -> 9932914.5 | J11: =I11/Combined_Portfolio!B14 -> 0.096603754 | L11: =A11 -> 6 | M11: {=IFERROR(SUMPRODUCT(Combined_Portfolio!$C$6:$C$13,(('Goals Input'!$E$6:$E$13-L11+1)*(('Goals Input'!$E$6:$E$13-L11+1>0))))/SUMPRODUCT(Combined_Portfolio!$C$6:$C$13,--(('Goals Input'!$E$6:$E$13-L11+1)>0)),0)} -> 13.528027 | N11: =IF(M11>15,80%,IF(M11>10,70%,IF(M11>7,60%,IF(M11>3,45%,25%)))) -> 0.7 | O11: =IF(M11>15,10%,IF(M11>10,20%,IF(M11>7,25%,IF(M11>3,40%,60%)))) -> 0.2 | P11: =IF(M11>15,5%,IF(M11>10,5%,IF(M11>7,10%,IF(M11>3,10%,10%)))) -> 0.05 | Q11: =5% -> 0.05
A12: 7 | B12: =I11 -> 9932914.5 | C12: 0.17 | D12: 0.06 | E12: 0.11 | F12: 0.09 | G12: =SUMPRODUCT(N12:Q12,C12:F12) -> 0.141 | H12: =Cash_Flow!D29 -> 1559871.3 | I12: =(B12*(1+G12))+H12 -> 12893327 | J12: =I12/Combined_Portfolio!B14 -> 0.1253956 | L12: =A12 -> 7 | M12: {=IFERROR(SUMPRODUCT(Combined_Portfolio!$C$6:$C$13,(('Goals Input'!$E$6:$E$13-L12+1)*(('Goals Input'!$E$6:$E$13-L12+1>0))))/SUMPRODUCT(Combined_Portfolio!$C$6:$C$13,--(('Goals Input'!$E$6:$E$13-L12+1)>0)),0)} -> 12.528027 | N12: =IF(M12>15,80%,IF(M12>10,70%,IF(M12>7,60%,IF(M12>3,45%,25%)))) -> 0.7 | O12: =IF(M12>15,10%,IF(M12>10,20%,IF(M12>7,25%,IF(M12>3,40%,60%)))) -> 0.2 | P12: =IF(M12>15,5%,IF(M12>10,5%,IF(M12>7,10%,IF(M12>3,10%,10%)))) -> 0.05 | Q12: =5% -> 0.05
A13: 8 | B13: =I12 -> 12893327 | C13: 0.07 | D13: 0.08 | E13: 0.08 | F13: 0.05 | G13: =SUMPRODUCT(N13:Q13,C13:F13) -> 0.0715 | H13: =Cash_Flow!D30 -> 1637864.9 | I13: =(B13*(1+G13))+H13 -> 15453065 | J13: =I13/Combined_Portfolio!B14 -> 0.15029064 | L13: =A13 -> 8 | M13: {=IFERROR(SUMPRODUCT(Combined_Portfolio!$C$6:$C$13,(('Goals Input'!$E$6:$E$13-L13+1)*(('Goals Input'!$E$6:$E$13-L13+1>0))))/SUMPRODUCT(Combined_Portfolio!$C$6:$C$13,--(('Goals Input'!$E$6:$E$13-L13+1)>0)),0)} -> 11.528027 | N13: =IF(M13>15,80%,IF(M13>10,70%,IF(M13>7,60%,IF(M13>3,45%,25%)))) -> 0.7 | O13: =IF(M13>15,10%,IF(M13>10,20%,IF(M13>7,25%,IF(M13>3,40%,60%)))) -> 0.2 | P13: =IF(M13>15,5%,IF(M13>10,5%,IF(M13>7,10%,IF(M13>3,10%,10%)))) -> 0.05 | Q13: =5% -> 0.05
A14: 9 | B14: =I13 -> 15453065 | C14: 0.01 | D14: 0.05 | E14: -0.05 | F14: 0.04 | G14: =SUMPRODUCT(N14:Q14,C14:F14) -> 0.0165 | H14: =Cash_Flow!D31 -> 1719758.1 | I14: =(B14*(1+G14))+H14 -> 17427798 | J14: =I14/Combined_Portfolio!B14 -> 0.16949615 | L14: =A14 -> 9 | M14: {=IFERROR(SUMPRODUCT(Combined_Portfolio!$C$6:$C$13,(('Goals Input'!$E$6:$E$13-L14+1)*(('Goals Input'!$E$6:$E$13-L14+1>0))))/SUMPRODUCT(Combined_Portfolio!$C$6:$C$13,--(('Goals Input'!$E$6:$E$13-L14+1)>0)),0)} -> 10.528027 | N14: =IF(M14>15,80%,IF(M14>10,70%,IF(M14>7,60%,IF(M14>3,45%,25%)))) -> 0.7 | O14: =IF(M14>15,10%,IF(M14>10,20%,IF(M14>7,25%,IF(M14>3,40%,60%)))) -> 0.2 | P14: =IF(M14>15,5%,IF(M14>10,5%,IF(M14>7,10%,IF(M14>3,10%,10%)))) -> 0.05 | Q14: =5% -> 0.05
A15: 10 | B15: =I14 -> 17427798 | C15: 0.09 | D15: 0.05 | E15: -0.03 | F15: 0.08 | G15: =SUMPRODUCT(N15:Q15,C15:F15) -> 0.0675 | H15: =Cash_Flow!D32 -> 1805746 | I15: =(B15*(1+G15))+H15 -> 20409921 | J15: =I15/Combined_Portfolio!B14 -> 0.19849914 | L15: =A15 -> 10 | M15: {=IFERROR(SUMPRODUCT(Combined_Portfolio!$C$6:$C$13,(('Goals Input'!$E$6:$E$13-L15+1)*(('Goals Input'!$E$6:$E$13-L15+1>0))))/SUMPRODUCT(Combined_Portfolio!$C$6:$C$13,--(('Goals Input'!$E$6:$E$13-L15+1)>0)),0)} -> 9.5280267 | N15: =IF(M15>15,80%,IF(M15>10,70%,IF(M15>7,60%,IF(M15>3,45%,25%)))) -> 0.6 | O15: =IF(M15>15,10%,IF(M15>10,20%,IF(M15>7,25%,IF(M15>3,40%,60%)))) -> 0.25 | P15: =IF(M15>15,5%,IF(M15>10,5%,IF(M15>7,10%,IF(M15>3,10%,10%)))) -> 0.1 | Q15: =5% -> 0.05
B17: Multiple Goal Simulation
A19: Year | B19: Emergency Fund | C19: Vacation | D19: Car Down Payment | E19: Education Fund | F19: Retirement | G19: Marriage | H19: Home Upgrade | I19: Philanthropy | J19: Emergency Fund SIP | K19: Vacation SIP | L19: Car Down Payment SIP | M19: Education Fund SIP | N19: Retirement SIP | O19: Marriage SIP | P19: Home Upgrade SIP | Q19: Philanthropy SIP | R19: Emergency Fund Return | S19: Vacation Return | T19: Car Return | U19: Education Return | V19: Retirement Return | W19: Marriage Return | X19: Home Return | Y19: Philanthropy Return | Z19: Emergency Funded | AA19: Vacation Funded | AB19: Car Funded | AC19: Education Funded | AD19: Retirement Funded | AE19: Marriage Funded | AF19: Home Funded | AG19: Philanthropy Funded
A20: 1 | B20: =Table4[[#This Row],[Emergency Fund SIP]] -> 5999.9296 | C20: =K20 -> 2543.9702 | D20: =L20 -> 6934.1243 | E20: =M20 -> 179554.64 | F20: =N20 -> 876144.7 | G20: =O20 -> 66808.13 | H20: =P20 -> 15877.758 | I20: =Q20 -> 10136.755 | J20: =$H$6* Combined_Portfolio!$C$6 -> 5999.9296 | K20: =$H$6* Combined_Portfolio!$C$7 -> 2543.9702 | L20: =$H$6* Combined_Portfolio!$C$8 -> 6934.1243 | M20: =$H$6* Combined_Portfolio!$C$9 -> 179554.64 | N20: =$H$6* Combined_Portfolio!$C$10 -> 876144.7 | O20: =$H$6* Combined_Portfolio!$C$11 -> 66808.13 | P20: =$H$6* Combined_Portfolio!$C$12 -> 15877.758 | Q20: =$H$6* Combined_Portfolio!$C$13 -> 10136.755 | R20: 0 | S20: -0.03 | T20: 0.01 | U20: 0.03 | V20: 0.1 | W20: 0.1 | X20: -0.03 | Y20: 0.06 | Z20: =B20 / Combined_Portfolio!$B$6 -> 0.011320622 | AA20: =C20 /Combined_Portfolio!$B$7 -> 0.011320622 | AB20: =D20 / Combined_Portfolio!$B$8 -> 0.011320622 | AC20: =E20/Combined_Portfolio!$B$9 -> 0.011320622 | AD20: =F20/Combined_Portfolio!$B$10 -> 0.011320622 | AE20: =G20/Combined_Portfolio!$B$11 -> 0.011320622 | AF20: =H20/Combined_Portfolio!$B$12 -> 0.011320622 | AG20: =I20/Combined_Portfolio!$B$13 -> 0.011320622
A21: 2 | B21: =B20*(1+R21)+J21 -> 12599.852 | C21: =C20*(1+S21)+K21 -> 5240.5785 | D21: =(D20*(1+T21))+L21 -> 14561.661 | E21: =(E20*(1+U21))+M21 -> 386042.47 | F21: =(F20*(1+V21))+N21 -> 1743527.9 | G21: =(G20*(1+W21))+O21 -> 142969.4 | H21: =(H20*(1+X21))+P21 -> 33978.402 | I21: =(I20*(1+Y21))+Q21 -> 21084.45 | J21: =J20*1.05 -> 6299.9261 | K21: =K20*1.05 -> 2671.1687 | L21: =L20*1.05 -> 7280.8305 | M21: =M20*1.05 -> 188532.37 | N21: =N20*1.05 -> 919951.93 | O21: =O20*1.05 -> 70148.537 | P21: =P20*1.05 -> 16671.646 | Q21: =Q20*1.05 -> 10643.593 | R21: 0.05 | S21: 0.01 | T21: 0.05 | U21: 0.1 | V21: -0.06 | W21: 0.09 | X21: 0.09 | Y21: 0.03 | Z21: =B21 / Combined_Portfolio!$B$6 -> 0.023773306 | AA21: =C21 /Combined_Portfolio!$B$7 -> 0.023320481 | AB21: =D21 / Combined_Portfolio!$B$8 -> 0.023773306 | AC21: =E21/Combined_Portfolio!$B$9 -> 0.024339337 | AD21: =F21/Combined_Portfolio!$B$10 -> 0.022528038 | AE21: =G21/Combined_Portfolio!$B$11 -> 0.024226131 | AF21: =H21/Combined_Portfolio!$B$12 -> 0.024226131 | AG21: =I21/Combined_Portfolio!$B$13 -> 0.023546894
A22: 3 | B22: =B21*(1+R22)+J22 -> 19844.767 | C22: =(C21*(1+S22))+K22 -> 7992.8999 | D22: =(D21*(1+T22))+L22 -> 21769.683 | E22: =(E21*(1+U22))+M22 -> 603303.58 | F22: =(F21*(1+V22))+N22 -> 2761783.3 | G22: =(G21*(1+W22))+O22 -> 213765.97 | H22: =(H21*(1+X22))+P22 -> 51483.63 | I22: =(I21*(1+Y22))+Q22 -> 32892.756 | J22: =J21*1.05 -> 6614.9224 | K22: =K21*1.05 -> 2804.7271 | L22: =L21*1.05 -> 7644.8721 | M22: =M21*1.05 -> 197958.99 | N22: =N21*1.05 -> 965949.53 | O22: =O21*1.05 -> 73655.964 | P22: =P21*1.05 -> 17505.228 | Q22: =Q21*1.05 -> 11175.772 | R22: 0.05 | S22: -0.01 | T22: -0.03 | U22: 0.05 | V22: 0.03 | W22: -0.02 | X22: 0 | Y22: 0.03 | Z22: =B22 / Combined_Portfolio!$B$6 -> 0.037442957 | AA22: =C22 /Combined_Portfolio!$B$7 -> 0.035568262 | AB22: =D22 / Combined_Portfolio!$B$8 -> 0.035541093 | AC22: =E22/Combined_Portfolio!$B$9 -> 0.03803729 | AD22: =F22/Combined_Portfolio!$B$10 -> 0.035684864 | AE22: =G22/Combined_Portfolio!$B$11 -> 0.036222594 | AF22: =H22/Combined_Portfolio!$B$12 -> 0.036707117 | AG22: =I22/Combined_Portfolio!$B$13 -> 0.036734286
A23: 4 | B23: =B22*(1+R23)+J23 -> 27187.331 | C23: =(C22*(1+S23))+K23 -> 10857.934 | D23: =(D22*(1+T23))+L23 -> 29796.799 | E23: =(E22*(1+U23))+M23 -> 799094.44 | F23: =(F22*(1+V23))+N23 -> 3858883.8 | G23: =(G22*(1+W23))+O23 -> 306068.36 | H23: =(H22*(1+X23))+P23 -> 70893.792 | I23: =(I22*(1+Y23))+Q23 -> 43969.462 | J23: =J22*1.05 -> 6945.6685 | K23: =K22*1.05 -> 2944.9635 | L23: =L22*1.05 -> 8027.1157 | M23: =M22*1.05 -> 207856.94 | N23: =N22*1.05 -> 1014247 | O23: =O22*1.05 -> 77338.762 | P23: =P22*1.05 -> 18380.489 | Q23: =Q22*1.05 -> 11734.561 | R23: 0.02 | S23: -0.01 | T23: 0 | U23: -0.02 | V23: 0.03 | W23: 0.07 | X23: 0.02 | Y23: -0.02 | Z23: =B23 / Combined_Portfolio!$B$6 -> 0.051296851 | AA23: =C23 /Combined_Portfolio!$B$7 -> 0.048317614 | AB23: =D23 / Combined_Portfolio!$B$8 -> 0.048646128 | AC23: =E23/Combined_Portfolio!$B$9 -> 0.050381579 | AD23: =F23/Combined_Portfolio!$B$10 -> 0.049860445 | AE23: =G23/Combined_Portfolio!$B$11 -> 0.051863211 | AF23: =H23/Combined_Portfolio!$B$12 -> 0.050546294 | AG23: =I23/Combined_Portfolio!$B$13 -> 0.049104635
A24: 5 | B24: =B23*(1+R24)+J24 -> 33664.663 | C24: =(C23*(1+S24))+K24 -> 14601.622 | D24: =(D23*(1+T24))+L24 -> 38225.27 | E24: =(E23*(1+U24))+M24 -> 1057298.9 | F24: =(F23*(1+V24))+N24 -> 5271142.7 | G24: =(G23*(1+W24))+O24 -> 393395.42 | H24: =(H23*(1+X24))+P24 -> 90902.244 | I24: =(I23*(1+Y24))+Q24 -> 57170.14 | J24: =J23*1.05 -> 7292.952 | K24: =K23*1.05 -> 3092.2116 | L24: =L23*1.05 -> 8428.4715 | M24: =M23*1.05 -> 218249.78 | N24: =N23*1.05 -> 1064959.4 | O24: =O23*1.05 -> 81205.7 | P24: =P23*1.05 -> 19299.514 | Q24: =Q23*1.05 -> 12321.289 | R24: -0.03 | S24: 0.06 | T24: 0 | U24: 0.05 | V24: 0.09 | W24: 0.02 | X24: 0.01 | Y24: 0.02 | Z24: =B24 / Combined_Portfolio!$B$6 -> 0.063518232 | AA24: =C24 /Combined_Portfolio!$B$7 -> 0.064976958 | AB24: =D24 / Combined_Portfolio!$B$8 -> 0.062406414 | AC24: =E24/Combined_Portfolio!$B$9 -> 0.066660945 | AD24: =F24/Combined_Portfolio!$B$10 -> 0.068108172 | AE24: =G24/Combined_Portfolio!$B$11 -> 0.066660761 | AF24: =H24/Combined_Portfolio!$B$12 -> 0.064812044 | AG24: =I24/Combined_Portfolio!$B$13 -> 0.063847015
A25: 6 | B25: =B24*(1+R25)+J25 -> 42668.849 | C25: =(C24*(1+S25))+K25 -> 17702.428 | D25: =(D24*(1+T25))+L25 -> 49368.682 | E25: =(E24*(1+U25))+M25 -> 1360472.1 | F25: =(F24*(1+V25))+N25 -> 6073081.5 | G25: =(G24*(1+W25))+O25 -> 514067 | H25: =(H24*(1+X25))+P25 -> 109348.69 | I25: =(I24*(1+Y25))+Q25 -> 68964.09 | J25: =J24*1.05 -> 7657.5996 | K25: =K24*1.05 -> 3246.8222 | L25: =L24*1.05 -> 8849.895 | M25: =M24*1.05 -> 229162.27 | N25: =N24*1.05 -> 1118207.3 | O25: =O24*1.05 -> 85265.985 | P25: =P24*1.05 -> 20264.49 | Q25: =Q24*1.05 -> 12937.353 | R25: 0.04 | S25: -0.01 | T25: 0.06 | U25: 0.07 | V25: -0.06 | W25: 0.09 | X25: -0.02 | Y25: -0.02 | Z25: =B25 / Combined_Portfolio!$B$6 -> 0.080507263 | AA25: =C25 /Combined_Portfolio!$B$7 -> 0.078775489 | AB25: =D25 / Combined_Portfolio!$B$8 -> 0.0805991 | AC25: =E25/Combined_Portfolio!$B$9 -> 0.085775512 | AD25: =F25/Combined_Portfolio!$B$10 -> 0.078469983 | AE25: =G25/Combined_Portfolio!$B$11 -> 0.087108531 | AF25: =H25/Combined_Portfolio!$B$12 -> 0.077964104 | AG25: =I25/Combined_Portfolio!$B$13 -> 0.077018376
A26: 7 | B26: =B25*(1+R26)+J26 -> 51989.394 | C26: =(C25*(1+S26))+K26 -> 21996.713 | D26: =(D25*(1+T26))+L26 -> 62116.879 | E26: =(E25*(1+U26))+M26 -> 1696325.6 | F26: =(F25*(1+V26))+N26 -> 7733045.7 | G26: =(G25*(1+W26))+O26 -> 629299.63 | H26: =(H25*(1+X26))+P26 -> 126252.46 | I26: =(I25*(1+Y26))+Q26 -> 82548.311 | J26: =J25*1.05 -> 8040.4795 | K26: =K25*1.05 -> 3409.1633 | L26: =L25*1.05 -> 9292.3898 | M26: =M25*1.05 -> 240620.39 | N26: =N25*1.05 -> 1174117.7 | O26: =O25*1.05 -> 89529.284 | P26: =P25*1.05 -> 21277.714 | Q26: =Q25*1.05 -> 13584.221 | R26: 0.03 | S26: 0.05 | T26: 0.07 | U26: 0.07 | V26: 0.08 | W26: 0.05 | X26: -0.04 | Y26: 0 | Z26: =B26 / Combined_Portfolio!$B$6 -> 0.098093197 | AA26: =C26 /Combined_Portfolio!$B$7 -> 0.09788498 | AB26: =D26 / Combined_Portfolio!$B$8 -> 0.10141175 | AC26: =E26/Combined_Portfolio!$B$9 -> 0.10695051 | AD26: =F26/Combined_Portfolio!$B$10 -> 0.099918298 | AE26: =G26/Combined_Portfolio!$B$11 -> 0.10663467 | AF26: =H26/Combined_Portfolio!$B$12 -> 0.090016256 | AG26: =I26/Combined_Portfolio!$B$13 -> 0.092189092
A27: 8 | B27: =B26*(1+R27)+J27 -> 59912.004 | C27: =(C26*(1+S27))+K27 -> 25576.334 | D27: =(D26*(1+T27))+L27 -> 75600.901 | E27: =(E26*(1+U27))+M27 -> 1847197.5 | F27: =(F26*(1+V27))+N27 -> 8501886.5 | G27: =(G26*(1+W27))+O27 -> 717012.38 | H27: =(H26*(1+X27))+P27 -> 147331.53 | I27: =(I26*(1+Y27))+Q27 -> 99288.193 | J27: =J26*1.05 -> 8442.5035 | K27: =K26*1.05 -> 3579.6215 | L27: =L26*1.05 -> 9757.0093 | M27: =M26*1.05 -> 252651.4 | N27: =N26*1.05 -> 1232823.6 | O27: =O26*1.05 -> 94005.749 | P27: =P26*1.05 -> 22341.6 | Q27: =Q26*1.05 -> 14263.432 | R27: -0.01 | S27: 0 | T27: 0.06 | U27: -0.06 | V27: -0.06 | W27: -0.01 | X27: -0.01 | Y27: 0.03 | Z27: =B27 / Combined_Portfolio!$B$6 -> 0.11304152 | AA27: =C27 /Combined_Portfolio!$B$7 -> 0.11381423 | AB27: =D27 / Combined_Portfolio!$B$8 -> 0.12342571 | AC27: =E27/Combined_Portfolio!$B$9 -> 0.11646273 | AD27: =F27/Combined_Portfolio!$B$10 -> 0.10985245 | AE27: =G27/Combined_Portfolio!$B$11 -> 0.12149758 | AF27: =H27/Combined_Portfolio!$B$12 -> 0.10504535 | AG27: =I27/Combined_Portfolio!$B$13 -> 0.11088402
A28: 9 | B28: =B27*(1+R28)+J28 -> 68776.633 | C28: =(C27*(1+S28))+K28 -> 30613.753 | D28: =(D27*(1+T28))+L28 -> 84333.743 | E28: =(E27*(1+U28))+M28 -> 2149425.4 | F28: =(F27*(1+V28))+N28 -> 10051408 | G28: =(G27*(1+W28))+O28 -> 851569.04 | H28: =(H27*(1+X28))+P28 -> 164896.95 | I28: =(I27*(1+Y28))+Q28 -> 116250.56 | J28: =J27*1.05 -> 8864.6287 | K28: =K27*1.05 -> 3758.6026 | L28: =L27*1.05 -> 10244.86 | M28: =M27*1.05 -> 265283.97 | N28: =N27*1.05 -> 1294464.8 | O28: =O27*1.05 -> 98706.036 | P28: =P27*1.05 -> 23458.68 | Q28: =Q27*1.05 -> 14976.604 | R28: 0 | S28: 0.05 | T28: -0.02 | U28: 0.02 | V28: 0.03 | W28: 0.05 | X28: -0.04 | Y28: 0.02 | Z28: =B28 / Combined_Portfolio!$B$6 -> 0.12976723 | AA28: =C28 /Combined_Portfolio!$B$7 -> 0.13623066 | AB28: =D28 / Combined_Portfolio!$B$8 -> 0.13768291 | AC28: =E28/Combined_Portfolio!$B$9 -> 0.1355177 | AD28: =F28/Combined_Portfolio!$B$10 -> 0.12987374 | AE28: =G28/Combined_Portfolio!$B$11 -> 0.14429817 | AF28: =H28/Combined_Portfolio!$B$12 -> 0.11756925 | AG28: =I28/Combined_Portfolio!$B$13 -> 0.12982741
A29: 10 | B29: =B28*(1+R29)+J29 -> 78084.493 | C29: =(C28*(1+S29))+K29 -> 34866.424 | D29: =(D28*(1+T29))+L29 -> 93404.171 | E29: =(E28*(1+U29))+M29 -> 2513950.6 | F29: =(F28*(1+V29))+N29 -> 11209568 | G29: =(G28*(1+W29))+O29 -> 1031851.6 | H29: =(H28*(1+X29))+P29 -> 182932.69 | I29: =(I28*(1+Y29))+Q29 -> 135463.51 | J29: =J28*1.05 -> 9307.8601 | K29: =K28*1.05 -> 3946.5327 | L29: =L28*1.05 -> 10757.103 | M29: =M28*1.05 -> 278548.17 | N29: =N28*1.05 -> 1359188 | O29: =O28*1.05 -> 103641.34 | P29: =P28*1.05 -> 24631.614 | Q29: =Q28*1.05 -> 15725.434 | R29: 0 | S29: 0.01 | T29: -0.02 | U29: 0.04 | V29: -0.02 | W29: 0.09 | X29: -0.04 | Y29: 0.03 | Z29: =B29 / Combined_Portfolio!$B$6 -> 0.14732923 | AA29: =C29 /Combined_Portfolio!$B$7 -> 0.15515496 | AB29: =D29 / Combined_Portfolio!$B$8 -> 0.15249125 | AC29: =E29/Combined_Portfolio!$B$9 -> 0.15850041 | AD29: =F29/Combined_Portfolio!$B$10 -> 0.14483827 | AE29: =G29/Combined_Portfolio!$B$11 -> 0.17484701 | AF29: =H29/Combined_Portfolio!$B$12 -> 0.13042848 | AG29: =I29/Combined_Portfolio!$B$13 -> 0.15128423
A30: 11 | B30: =B29*(1+R30)+J30 -> 84734.366 | C30: =(C29*(1+S30))+K30 -> 40404.94 | D30: =(D29*(1+T30))+L30 -> 109369.34 | E30: =(E29*(1+U30))+M30 -> 2831565.7 | F30: =(F29*(1+V30))+N30 -> 13533480 | G30: =(G29*(1+W30))+O30 -> 1130356.5 | H30: =(H29*(1+X30))+P30 -> 210625.21 | I30: =(I29*(1+Y30))+Q30 -> 151975.22 | J30: =J29*1.05 -> 9773.2531 | K30: =K29*1.05 -> 4143.8593 | L30: =L29*1.05 -> 11294.958 | M30: =M29*1.05 -> 292475.58 | N30: =N29*1.05 -> 1427147.4 | O30: =O29*1.05 -> 108823.4 | P30: =P29*1.05 -> 25863.195 | Q30: =Q29*1.05 -> 16511.706 | R30: -0.04 | S30: 0.04 | T30: 0.05 | U30: 0.01 | V30: 0.08 | W30: -0.01 | X30: 0.01 | Y30: 0 | Z30: =B30 / Combined_Portfolio!$B$6 -> 0.15987616 | AA30: =C30 /Combined_Portfolio!$B$7 -> 0.17980126 | AB30: =D30 / Combined_Portfolio!$B$8 -> 0.17855592 | AC30: =E30/Combined_Portfolio!$B$9 -> 0.17852552 | AD30: =F30/Combined_Portfolio!$B$10 -> 0.17486543 | AE30: =G30/Combined_Portfolio!$B$11 -> 0.19153864 | AF30: =H30/Combined_Portfolio!$B$12 -> 0.15017286 | AG30: =I30/Combined_Portfolio!$B$13 -> 0.16972433
A31: 12 | B31: =B30*(1+R31)+J31 -> 94148.938 | C31: =(C30*(1+S31))+K31 -> 45968.14 | D31: =(D30*(1+T31))+L31 -> 126697.51 | E31: =(E30*(1+U31))+M31 -> 3308559 | F31: =(F30*(1+V31))+N31 -> 14896650 | G31: =(G30*(1+W31))+O31 -> 1323746 | H31: =(H30*(1+X31))+P31 -> 231462.8 | I31: =(I30*(1+Y31))+Q31 -> 169312.51 | J31: =J30*1.05 -> 10261.916 | K31: =K30*1.05 -> 4351.0523 | L31: =L30*1.05 -> 11859.706 | M31: =M30*1.05 -> 307099.36 | N31: =N30*1.05 -> 1498504.8 | O31: =O30*1.05 -> 114264.57 | P31: =P30*1.05 -> 27156.354 | Q31: =Q30*1.05 -> 17337.291 | R31: -0.01 | S31: 0.03 | T31: 0.05 | U31: 0.06 | V31: -0.01 | W31: 0.07 | X31: -0.03 | Y31: 0 | Z31: =B31 / Combined_Portfolio!$B$6 -> 0.17763951 | AA31: =C31 /Combined_Portfolio!$B$7 -> 0.20455741 | AB31: =D31 / Combined_Portfolio!$B$8 -> 0.20684582 | AC31: =E31/Combined_Portfolio!$B$9 -> 0.20859915 | AD31: =F31/Combined_Portfolio!$B$10 -> 0.19247888 | AE31: =G31/Combined_Portfolio!$B$11 -> 0.22430845 | AF31: =H31/Combined_Portfolio!$B$12 -> 0.16502978 | AG31: =I31/Combined_Portfolio!$B$13 -> 0.18908644
A32: 13 | B32: =B31*(1+R32)+J32 -> 101157.99 | C32: =(C31*(1+S32))+K32 -> 52375.471 | D32: =(D31*(1+T32))+L32 -> 140417.18 | E32: =(E31*(1+U32))+M32 -> 3697184.5 | F32: =(F31*(1+V32))+N32 -> 17959745 | G32: =(G31*(1+W32))+O32 -> 1536386 | H32: =(H31*(1+X32))+P32 -> 257662.35 | I32: =(I31*(1+Y32))+Q32 -> 195982.29 | J32: =J31*1.05 -> 10775.012 | K32: =K31*1.05 -> 4568.6049 | L32: =L31*1.05 -> 12452.691 | M32: =M31*1.05 -> 322454.33 | N32: =N31*1.05 -> 1573430 | O32: =O31*1.05 -> 119977.8 | P32: =P31*1.05 -> 28514.172 | Q32: =Q31*1.05 -> 18204.155 | R32: -0.04 | S32: 0.04 | T32: 0.01 | U32: 0.02 | V32: 0.1 | W32: 0.07 | X32: -0.01 | Y32: 0.05 | Z32: =B32 / Combined_Portfolio!$B$6 -> 0.19086414 | AA32: =C32 /Combined_Portfolio!$B$7 -> 0.23306991 | AB32: =D32 / Combined_Portfolio!$B$8 -> 0.22924449 | AC32: =E32/Combined_Portfolio!$B$9 -> 0.23310135 | AD32: =F32/Combined_Portfolio!$B$10 -> 0.23205698 | AE32: =G32/Combined_Portfolio!$B$11 -> 0.26034025 | AF32: =H32/Combined_Portfolio!$B$12 -> 0.18370969 | AG32: =I32/Combined_Portfolio!$B$13 -> 0.21887097
A33: 14 | B33: =B32*(1+R33)+J33 -> 115506.49 | C33: =(C32*(1+S33))+K33 -> 56648.751 | D33: =(D32*(1+T33))+L33 -> 152088.33 | E33: =(E32*(1+U33))+M33 -> 3887874.1 | F33: =(F32*(1+V33))+N33 -> 18713860 | G33: =(G32*(1+W33))+O33 -> 1754545.9 | H33: =(H32*(1+X33))+P33 -> 310791.84 | I33: =(I32*(1+Y33))+Q33 -> 226855.59 | J33: =J32*1.05 -> 11313.762 | K33: =K32*1.05 -> 4797.0352 | L33: =L32*1.05 -> 13075.326 | M33: =M32*1.05 -> 338577.05 | N33: =N32*1.05 -> 1652101.5 | O33: =O32*1.05 -> 125976.69 | P33: =P32*1.05 -> 29939.881 | Q33: =Q32*1.05 -> 19114.363 | R33: 0.03 | S33: -0.01 | T33: -0.01 | U33: -0.04 | V33: -0.05 | W33: 0.06 | X33: 0.09 | Y33: 0.06 | Z33: =B33 / Combined_Portfolio!$B$6 -> 0.21793678 | AA33: =C33 /Combined_Portfolio!$B$7 -> 0.25208594 | AB33: =D33 / Combined_Portfolio!$B$8 -> 0.24829876 | AC33: =E33/Combined_Portfolio!$B$9 -> 0.24512401 | AD33: =F33/Combined_Portfolio!$B$10 -> 0.24180085 | AE33: =G33/Combined_Portfolio!$B$11 -> 0.29730739 | AF33: =H33/Combined_Portfolio!$B$12 -> 0.22159029 | AG33: =I33/Combined_Portfolio!$B$13 -> 0.25334995
A34: 15 | B34: =B33*(1+R34)+J34 -> 133161.27 | C34: =(C33*(1+S34))+K34 -> 63951.588 | D34: =(D33*(1+T34))+L34 -> 167338.31 | E34: =(E33*(1+U34))+M34 -> 4126743.8 | F34: =(F33*(1+V34))+N34 -> 21384259 | G34: =(G33*(1+W34))+O34 -> 1957003.2 | H34: =(H33*(1+X34))+P34 -> 370199.98 | I34: =(I33*(1+Y34))+Q34 -> 255999.89 | J34: =J33*1.05 -> 11879.45 | K34: =K33*1.05 -> 5036.8869 | L34: =L33*1.05 -> 13729.092 | M34: =M33*1.05 -> 355505.9 | N34: =N33*1.05 -> 1734706.6 | O34: =O33*1.05 -> 132275.53 | P34: =P33*1.05 -> 31436.875 | Q34: =Q33*1.05 -> 20070.081 | R34: 0.05 | S34: 0.04 | T34: 0.01 | U34: -0.03 | V34: 0.05 | W34: 0.04 | X34: 0.09 | Y34: 0.04 | Z34: =B34 / Combined_Portfolio!$B$6 -> 0.25124768 | AA34: =C34 /Combined_Portfolio!$B$7 -> 0.28458343 | AB34: =D34 / Combined_Portfolio!$B$8 -> 0.27319581 | AC34: =E34/Combined_Portfolio!$B$9 -> 0.26018435 | AD34: =F34/Combined_Portfolio!$B$10 -> 0.27630495 | AE34: =G34/Combined_Portfolio!$B$11 -> 0.33161374 | AF34: =H34/Combined_Portfolio!$B$12 -> 0.26394747 | AG34: =I34/Combined_Portfolio!$B$13 -> 0.28589801
R35: -0.03 | S35: 0.04 | T35: -0.02 | U35: -0.06 | V35: 0.02 | W35: 0.01 | X35: -0.01 | Y35: 0.02

Sheet Cash_Flow
B3: Cash_Flow
B4: Monthy Cash Flow
A5: Month | B5: Income | C5: Fixed Expenses | D5: Variable Expenses | E5: Total Expenses | F5: SIP Total | G5: Surplus | H5: Status | I5: Saving %
A6: Jan | B6: 250000 | C6: 80000 | D6: 30000 | E6: =C6+D6 -> 110000 | F6: =SUM('Goals Input'!I6:I13) -> 97000 | G6: =B6-E6-F6 -> 43000 | H6: =IF(G6>=0,"Healthy","Deficit") -> Healthy | I6: =G6/B6 -> 0.172
A7: Feb | B7: 250000 | C7: 80000 | D7: 28000 | E7: =C7+D7 -> 108000 | F7: =SUM('Goals Input'!I6:I13) -> 97000 | G7: =B7-E7-F7 -> 45000 | H7: =IF(G7>=0,"Healthy","Deficit") -> Healthy | I7: =G7/B7 -> 0.18 | K7: Control input (every year)
A8: Mar | B8: 250000 | C8: 80000 | D8: 32000 | E8: =C8+D8 -> 112000 | F8: =SUM('Goals Input'!I6:I13) -> 97000 | G8: =B8-E8-F8 -> 41000 | H8: =IF(G8>=0,"Healthy","Deficit") -> Healthy | I8: =G8/B8 -> 0.164 | K8: Salary Growth | L8: 0.08
A9: Apr | B9: 250000 | C9: 80000 | D9: 35000 | E9: =C9+D9 -> 115000 | F9: =SUM('Goals Input'!I6:I13) -> 97000 | G9: =B9-E9-F9 -> 38000 | H9: =IF(G9>=0,"Healthy","Deficit") -> Healthy | I9: =G9/B9 -> 0.152 | K9: Expense Inflation | L9: 0.06
A10: May | B10: 250000 | C10: 80000 | D10: 40000 | E10: =C10+D10 -> 120000 | F10: =SUM('Goals Input'!I6:I13) -> 97000 | G10: =B10-E10-F10 -> 33000 | H10: =IF(G10>=0,"Healthy","Deficit") -> Healthy | I10: =G10/B10 -> 0.132 | K10: SIP Growth | L10: 0.05
A11: Jun | B11: 250000 | C11: 80000 | D11: 45000 | E11: =C11+D11 -> 125000 | F11: =SUM('Goals Input'!I6:I13) -> 97000 | G11: =B11-E11-F11 -> 28000 | H11: =IF(G11>=0,"Healthy","Deficit") -> Healthy | I11: =G11/B11 -> 0.112
A12: Jul | B12: 250000 | C12: 80000 | D12: 42000 | E12: =C12+D12 -> 122000 | F12: =SUM('Goals Input'!I6:I13) -> 97000 | G12: =B12-E12-F12 -> 31000 | H12: =IF(G12>=0,"Healthy","Deficit") -> Healthy | I12: =G12/B12 -> 0.124
A13: Aug | B13: 250000 | C13: 80000 | D13: 38000 | E13: =C13+D13 -> 118000 | F13: =SUM('Goals Input'!I6:I13) -> 97000 | G13: =B13-E13-F13 -> 35000 | H13: =IF(G13>=0,"Healthy","Deficit") -> Healthy | I13: =G13/B13 -> 0.14
A14: Sep | B14: 250000 | C14: 80000 | D14: 36000 | E14: =C14+D14 -> 116000 | F14: =SUM('Goals Input'!I6:I13) -> 97000 | G14: =B14-E14-F14 -> 37000 | H14: =IF(G14>=0,"Healthy","Deficit") -> Healthy | I14: =G14/B14 -> 0.148
A15: Oct | B15: 250000 | C15: 80000 | D15: 34000 | E15: =C15+D15 -> 114000 | F15: =SUM('Goals Input'!I6:I13) -> 97000 | G15: =B15-E15-F15 -> 39000 | H15: =IF(G15>=0,"Healthy","Deficit") -> Healthy | I15: =G15/B15 -> 0.156
A16: Nov | B16: 250000 | C16: 80000 | D16: 30000 | E16: =C16+D16 -> 110000 | F16: =SUM('Goals Input'!I6:I13) -> 97000 | G16: =B16-E16-F16 -> 43000 | H16: =IF(G16>=0,"Healthy","Deficit") -> Healthy | I16: =G16/B16 -> 0.172
A17: Dec | B17: 250000 | C17: 80000 | D17: 45000 | E17: =C17+D17 -> 125000 | F17: =SUM('Goals Input'!I6:I13) -> 97000 | G17: =B17-E17-F17 -> 28000 | H17: =IF(G17>=0,"Healthy","Deficit") -> Healthy | I17: =G17/B17 -> 0.112
A18: Annual Total | B18: =SUM(B6:B17) -> 3000000 | C18: =SUM(C6:C17) -> 960000 | D18: =SUM(D6:D17) -> 435000 | E18: =SUM(C18,D18) -> 1395000 | F18: =SUM(F6:F17) -> 1164000 | G18: =B18-E18-F18 -> 441000 | H18: =IF(G18>=0,"Healthy","Deficit") -> Healthy | I18: =G18/B18 -> 0.147
B21: Annual Cash Flow
A22: Year | B22: Total Income | C22: Total Expenses | D22: Total SIP (5% incerse every year) | E22: Surplus | F22: Savings %
A23: Year 1 | B23: =SUM(B6:B17) -> 3000000 | C23: =SUM(E6:E17) -> 1395000 | D23: =SUM(F6:F17) -> 1164000 | E23: =B23-C23-D23 -> 441000 | F23: =E23/B23 -> 0.147
A24: Year 2 | B24: =B23*(1+$L$8) -> 3240000 | C24: =C23*(1+$L$9) -> 1478700 | D24: =D23*(1+5%) -> 1222200 | E24: =B24-C24-D24 -> 539100 | F24: =E24/B24 -> 0.16638889
A25: Year 3 | B25: =B24*(1+$L$8) -> 3499200 | C25: =C24*(1+$L$9) -> 1567422 | D25: =D24*(1+5%) -> 1283310 | E25: =B25-C25-D25 -> 648468 | F25: =E25/B25 -> 0.18531893
A26: Year 4 | B26: =B25*(1+$L$8) -> 3779136 | C26: =C25*(1+$L$9) -> 1661467.3 | D26: =D25*(1+5%) -> 1347475.5 | E26: =B26-C26-D26 -> 770193.18 | F26: =E26/B26 -> 0.20380139
A27: Year 5 | B27: =B26*(1+$L$8) -> 4081466.9 | C27: =C26*(1+$L$9) -> 1761155.4 | D27: =D26*(1+5%) -> 1414849.3 | E27: =B27-C27-D27 -> 905462.25 | F27: =E27/B27 -> 0.22184726
A28: Year 6 | B28: =B27*(1+$L$8) -> 4407984.2 | C28: =C27*(1+$L$9) -> 1866824.7 | D28: =D27*(1+5%) -> 1485591.7 | E28: =B28-C28-D28 -> 1055567.8 | F28: =E28/B28 -> 0.23946724
A29: Year 7 | B29: =B28*(1+$L$8) -> 4760623 | C29: =C28*(1+$L$9) -> 1978834.2 | D29: =D28*(1+5%) -> 1559871.3 | E29: =B29-C29-D29 -> 1221917.5 | F29: =E29/B29 -> 0.25667176
A30: Year 8 | B30: =B29*(1+$L$8) -> 5141472.8 | C30: =C29*(1+$L$9) -> 2097564.2 | D30: =D29*(1+5%) -> 1637864.9 | E30: =B30-C30-D30 -> 1406043.7 | F30: =E30/B30 -> 0.273471
A31: Year 9 | B31: =B30*(1+$L$8) -> 5552790.6 | C31: =C30*(1+$L$9) -> 2223418.1 | D31: =D30*(1+5%) -> 1719758.1 | E31: =B31-C31-D31 -> 1609614.4 | F31: =E31/B31 -> 0.28987486
A32: Year 10 | B32: =B31*(1+$L$8) -> 5997013.9 | C32: =C31*(1+$L$9) -> 2356823.1 | D32: =D31*(1+5%) -> 1805746 | E32: =B32-C32-D32 -> 1834444.7 | F32: =E32/B32 -> 0.30589302

Sheet Dashboard
A1: GOAL BASED PORTFOLIO REBALANCING DASHBOARD | AA1: Data As Of Year | AB1: 4
B6: TOTAL PORTFOLIO VALUE | F6: TOTAL GOALS | K6: GOALS ACHIEVED | Q6: GOAL FUNDING RATIO | T6: CURRENT RISK STAGE | Y6: REBALANCE REQUIRED
B7: =Simulation!I15 -> 20409921 | F7: =COUNTA('Goals Input'!A6:A13) -> 8 | K7: =COUNTIF(AG16:AG23,"Achieved") -> 0 | Q7: =Simulation!I15/'Goals Input'!G14 -> 0.19849914 | T7: =IF(MAX(Table7[Year])>15, "Aggressive", IF(MAX(Table7[Year])>10, "Growth", IF(MAX(Table7[Year])>7, "Moderate", IF(MAX(Table7[Year])>3, "Balanced", "Conservative")))) -> Moderate | U7: Years Left: 5 | Y7: =COUNTIF(Table21[[Overall Portfolio Rebalance Flag ]],"Rebalance Portfolio") -> 4 | Z7: Assets Out of Range | AH7: Asset | AI7: Weight | AL7: Asset | AM7: Drift
AH8: Equity | AI8: =Simulation!N15 -> 0.6 | AL8: Equity | AM8: =Combined_Portfolio!D20 -> 0.0088324414
AH9: Debt | AI9: =Simulation!O15 -> 0.25 | AL9: Debt | AM9: =Combined_Portfolio!D21 -> -0.013484532
AH10: Metals | AI10: =Simulation!P15 -> 0.1 | AL10: Metals | AM10: =Combined_Portfolio!D22 -> 0
AH11: Alternative | AI11: =Simulation!Q15 -> 0.05 | AL11: Alternative | AM11: =Combined_Portfolio!D23 -> 0.0046520905
AH15: Goals | AI15: Target | AJ15: Achieved
AG16: =IF(AJ16>=AI16,"Achieved","Pending") -> Pending | AH16: {=Table12[Goal Name]} -> Emergency Fund | AI16: {=Table12[Future Value]} -> 530000 | AJ16: =Simulation!B34 -> 133161.27
AG17: =IF(AJ17>=AI17,"Achieved","Pending") -> Pending | AH17: Vacation | AI17: 224720 | AJ17: =Simulation!C34 -> 63951.588
AG18: =IF(AJ18>=AI18,"Achieved","Pending") -> Pending | AH18: Car Down Payment | AI18: 612521.5 | AJ18: =Simulation!D34 -> 167338.31
AG19: =IF(AJ19>=AI19,"Achieved","Pending") -> Pending | AH19: Education Fund | AI19: 15860846 | AJ19: =Simulation!E34 -> 4126743.8
AG20: =IF(AJ20>=AI20,"Achieved","Pending") -> Pending | AH20: Retirement | AI20: 77393689 | AJ20: =Simulation!F34 -> 21384259
AG21: =IF(AJ21>=AI21,"Achieved","Pending") -> Pending | AH21: Marriage | AI21: 5901454.1 | AJ21: =Simulation!G34 -> 1957003.2
AG22: =IF(AJ22>=AI22,"Achieved","Pending") -> Pending | AH22: Home Upgrade | AI22: 1402551.7 | AJ22: =Simulation!H34 -> 370199.98
AG23: =IF(AJ23>=AI23,"Achieved","Pending") -> Pending | AH23: Philanthropy | AI23: 895423.85 | AJ23: =Simulation!I34 -> 255999.89
H63: 3
